LICENSE
MANIFEST.in
README.md
requirements.txt
setup.py
pyauto/__init__.py
pyauto.shell.egg-info/PKG-INFO
pyauto.shell.egg-info/SOURCES.txt
pyauto.shell.egg-info/dependency_links.txt
pyauto.shell.egg-info/requires.txt
pyauto.shell.egg-info/top_level.txt
pyauto/shell/__init__.py
pyauto/shell/config.py
pyauto/shell/package.yml