Metadata-Version: 1.0
Name: pyauto.shell
Version: 1.0.0a1
Summary: A shell command execution module
Home-page: https://github.com/adamjaso/pyauto/tree/master/shell
Author: Adam Jaso
Author-email: UNKNOWN
License: GNU General Public License V2
Platform: UNKNOWN
